{
  "name": "barber-demo",
  "industry": "Beauty",
  "title": "Northline Barbers",
  "description": "A premium barbershop demo website built for BrandLifters portfolio testing.",
  "tags": ["barber", "grooming", "local-business"],
  "features": ["Per-barber booking", "Service & pricing menu", "Loyalty / referral hooks", "Instagram feed", "Hours & directions"],
  "primaryColor": "#111111",
  "accentColor": "#C9A84C",
  "accentFrom": "#115e5b",
  "accentTo": "#0fb5b1",
  "repoName": "demo-barber-shop",
  "vercelProjectName": "demo-barber-shop",
  "localPath": "C:/Users/abdul/brandlifters-material/brandlifters-demo/barber-demo",
  "previewUrl": ""
}
